alumathprimes/__init__.py
alumathprimes/multiplier.py
alumathprimess/__init__.py
alumathprimess/multiplier.py
alumathprimes-0.1.1.dist-info/METADATA
alumathprimes-0.1.1.dist-info/WHEEL
alumathprimes-0.1.1.dist-info/top_level.txt
alumathprimes-0.1.1.dist-info/RECORD
