Metadata-Version: 2.4
Name: alumathprimes
Version: 0.1.1
Summary: A simple library to multiply matrices of different dimensions
Author: Primes
Classifier: Programming Language :: Python :: 3
Classifier: License :: OSI Approved :: MIT License
Classifier: Operating System :: OS Independent
Requires-Python: >=3.6
Dynamic: author
Dynamic: classifier
Dynamic: description
Dynamic: description-content-type
Dynamic: requires-python
Dynamic: summary
